{"form": {"id": "Ghi-Danh-Nhập-Học", "title": "Ghi Danh Nhập Học", "fields": [{"id": "field_0", "name": "Họ và Tên", "type": "short_answer", "mapping": "name", "helpText": "", "required": true, "placeholder": "Nhập họ và tên"}, {"id": "field_1", "name": "Pháp Danh", "type": "short_answer", "helpText": "", "required": false, "placeholder": "Nhập pháp danh"}, {"id": "field_2", "name": "Ngày Sinh", "type": "date", "helpText": "Định dạng: dd/mm/yyyy", "required": false, "placeholder": "dd/mm/yyyy"}, {"id": "field_3", "name": "Giới Tính", "type": "multiple_choice", "options": ["Nam", "Nữ"], "helpText": "", "required": true, "placeholder": ""}, {"id": "field_4", "name": "Email", "type": "email_address", "mapping": "email", "helpText": "", "required": true, "placeholder": "example@email.com"}, {"id": "field_5", "name": "Số Điện Thoại", "type": "phone_number", "helpText": "", "required": true, "placeholder": "### ### ####"}, {"id": "field_6", "name": "Chương Trình Học", "type": "dropdown", "options": ["Sơ Cấp", "Trung Cấp", "Cao Đẳng"], "helpText": "", "required": true, "placeholder": ""}, {"id": "field_7", "name": "Hình Thức Tham Gia", "type": "dropdown", "options": ["Trực Tiếp", "Trực Tuyến"], "helpText": "", "required": true, "placeholder": ""}]}, "settings": {"submit": "email", "emailBody": "Hello {{name}} I hope this works!", "emailSubject": "Hello {{name}} I hope this works!", "emailTokenMap": {"field_0": "name", "field_1": "pháp danh", "field_2": "ngày sinh", "field_3": "giới tính", "field_4": "email", "field_5": "số điện thoại", "field_6": "chương trình học", "field_7": "hình thức tham gia"}, "successMessage": "", "emailTemplateId": "form--ghi-danh-nhap-hoc-2"}}
